LICENSE
impler/__init__.py
impler/exceptions.py
impler/main.py
impler-0.1.0.dist-info/LICENSE
impler-0.1.0.dist-info/WHEEL
impler-0.1.0.dist-info/METADATA
impler-0.1.0.dist-info/RECORD
