Metadata-Version: 2.1
Name: impler
Version: 0.1.0
Summary: 
Home-page: https://github.com/roman-right/impler
License: Apache-2.0
Keywords: impl,impler,implementation,pattern,sync,async,python
Author: Roman
Author-email: roman-right@protonmail.com
Requires-Python: >=3.7,<4.0
Classifier: License :: OSI Approved :: Apache Software License
Classifier: Programming Language :: Python :: 3
Classifier: Programming Language :: Python :: 3.7
Classifier: Programming Language :: Python :: 3.8
Classifier: Programming Language :: Python :: 3.9
Requires-Dist: asyncio (>=3.4,<4.0)
Project-URL: Repository, https://github.com/roman-right/impler
